stravavis/__init__.py
stravavis/__main__.py
stravavis/cli.py
stravavis/plot_calendar.py
stravavis/plot_dumbbell.py
stravavis/plot_elevations.py
stravavis/plot_facets.py
stravavis/plot_landscape.py
stravavis/plot_map.py
stravavis/process_activities.py
stravavis/process_data.py
stravavis-0.6.0.dist-info/METADATA
stravavis-0.6.0.dist-info/WHEEL
stravavis-0.6.0.dist-info/entry_points.txt
stravavis-0.6.0.dist-info/licenses/LICENSE
stravavis-0.6.0.dist-info/RECORD
