Metadata-Version: 2.4
Name: stravavis
Version: 0.6.0
Summary: Create artistic visualisations with your exercise data
Project-URL: Homepage, https://github.com/marcusvolz/strava_py
Project-URL: Source, https://github.com/marcusvolz/strava_py
Author: Marcus Volz
Maintainer: Hugo van Kemenade
License-Expression: MIT
License-File: LICENSE
Keywords: artistic,artistic visualisations,exercise,exercise data,strava,visualisation
Classifier: Development Status :: 3 - Alpha
Classifier: License :: OSI Approved :: MIT License
Classifier: Programming Language :: Python :: 3 :: Only
Classifier: Programming Language :: Python :: 3.10
Classifier: Programming Language :: Python :: 3.11
Classifier: Programming Language :: Python :: 3.12
Classifier: Programming Language :: Python :: 3.13
Classifier: Programming Language :: Python :: 3.14
Classifier: Topic :: Artistic Software
Classifier: Topic :: Multimedia :: Graphics
Classifier: Topic :: Scientific/Engineering :: Visualization
Requires-Python: >=3.10
Requires-Dist: calmap>=0.0.11
Requires-Dist: fit2gpx
Requires-Dist: gpxpy
Requires-Dist: matplotlib
Requires-Dist: pandas>=2
Requires-Dist: plotnine
Requires-Dist: rich
Requires-Dist: seaborn
Requires-Dist: setuptools; python_version >= '3.12'
